{
  "ESTJ": { "writer": "ESTJ", "img": "ESTJ.png" },
  "ESTP": { "writer": "ESTP", "img": "ESTP.png" },
  "ESFJ": { "writer": "ESFJ", "img": "ESFJ.png" },
  "ESFP": { "writer": "ESFP", "img": "ESFP.png" },
  "ENTJ": { "writer": "ENTJ", "img": "ENTJ.png" },
  "ENTP": { "writer": "ENTP", "img": "ENTP.png" },
  "ENFJ": { "writer": "ENFJ", "img": "ENFJ.png" },
  "ENFP": { "writer": "ENFP", "img": "ENFP.png" },
  "ISTJ": { "writer": "ISTJ", "img": "ISTJ.png" },
  "ISTP": { "writer": "ISTP", "img": "ISTP.png" },
  "ISFJ": { "writer": "ISFJ", "img": "ISFJ.png" },
  "ISFP": { "writer": "ISFP", "img": "ISFP.png" },
  "INTJ": { "writer": "INTJ", "img": "INTJ.png" },
  "INTP": { "writer": "INTP", "img": "INTP.png" },
  "INFJ": { "writer": "INFJ", "img": "INFJ.png" },
  "INFP": { "writer": "INFP", "img": "INFP.png" }
}
